<?xml version="1.0" encoding="utf-8"?><toc><breadcrumbs><li><a href="910080bc-65d0-9991-5d77-6141ec31bbbf.htm">Docs</a></li><li><a href="910080bc-65d0-9991-5d77-6141ec31bbbf.htm">Chat<wbr />Server</a></li></breadcrumbs><tocItems><li><a id="c9bd3922-b347-2f4a-76f7-01825d00e603" class="has-submenu" href="c9bd3922-b347-2f4a-76f7-01825d00e603.htm"><span data-tocFile="../toc/IDAA.xml" class="icon toggle" onclick="ToggleExpandCollapse(this); return false;"><i class="fa fa-angle-right"> </i></span>Chat<wbr />Client</a><ul class="toc-menu is-hidden"> </ul></li><li><a id="34d3c90d-da72-0054-ec5c-3591d807c9c0" class="has-submenu" href="34d3c90d-da72-0054-ec5c-3591d807c9c0.htm"><span data-tocFile="../toc/IDBA.xml" class="icon toggle" onclick="ToggleExpandCollapse(this); return false;"><i class="fa fa-angle-right"> </i></span>Server</a><ul class="toc-menu is-hidden"> </ul></li><li><a id="aa091c0b-077d-6cfa-d83c-04438c00f977" class="has-submenu" href="aa091c0b-077d-6cfa-d83c-04438c00f977.htm"><span data-tocFile="../toc/IDCA.xml" class="icon toggle" onclick="ToggleExpandCollapse(this); return false;"><i class="fa fa-angle-right"> </i></span>Server<wbr />Db<wbr />Context</a><ul class="toc-menu is-hidden"> </ul></li></tocItems></toc>